clipsai_jp/__init__.py
clipsai_jp/clip/__init__.py
clipsai_jp/clip/clip.py
clipsai_jp/clip/clipfinder.py
clipsai_jp/clip/exceptions.py
clipsai_jp/clip/gemini_clipfinder.py
clipsai_jp/clip/text_embedder.py
clipsai_jp/clip/texttiler.py
clipsai_jp/diarize/__init__.py
clipsai_jp/diarize/exceptions.py
clipsai_jp/diarize/pyannote.py
clipsai_jp/filesys/__init__.py
clipsai_jp/filesys/dir.py
clipsai_jp/filesys/exceptions.py
clipsai_jp/filesys/file.py
clipsai_jp/filesys/json_file.py
clipsai_jp/filesys/manager.py
clipsai_jp/filesys/object.py
clipsai_jp/media/__init__.py
clipsai_jp/media/audio_file.py
clipsai_jp/media/audiovideo_file.py
clipsai_jp/media/editor.py
clipsai_jp/media/exceptions.py
clipsai_jp/media/image_file.py
clipsai_jp/media/media_file.py
clipsai_jp/media/temporal_media_file.py
clipsai_jp/media/video_file.py
clipsai_jp/resize/__init__.py
clipsai_jp/resize/crops.py
clipsai_jp/resize/exceptions.py
clipsai_jp/resize/img_proc.py
clipsai_jp/resize/rect.py
clipsai_jp/resize/resize.py
clipsai_jp/resize/resizer.py
clipsai_jp/resize/segment.py
clipsai_jp/resize/vid_proc.py
clipsai_jp/transcribe/__init__.py
clipsai_jp/transcribe/exceptions.py
clipsai_jp/transcribe/japanese_sentence_splitter.py
clipsai_jp/transcribe/transcriber.py
clipsai_jp/transcribe/transcription.py
clipsai_jp/transcribe/transcription_element.py
clipsai_jp/utils/__init__.py
clipsai_jp/utils/config_manager.py
clipsai_jp/utils/conversions.py
clipsai_jp/utils/exception_handler.py
clipsai_jp/utils/exceptions.py
clipsai_jp/utils/pytorch.py
clipsai_jp/utils/type_checker.py
clipsai_jp/utils/utils.py
clipsai_jp-1.0.4.dist-info/licenses/LICENSE
clipsai_jp-1.0.4.dist-info/METADATA
clipsai_jp-1.0.4.dist-info/WHEEL
clipsai_jp-1.0.4.dist-info/top_level.txt
clipsai_jp-1.0.4.dist-info/RECORD
